README.md
setup.py
test/__init__.py
test/test_account.py
test/test_account_currency.py
test/test_account_daily_sum_median.py
test/test_accounts_api.py
test/test_bank_api.py
test/test_bankconnection.py
test/test_categories_api.py
test/test_category.py
test/test_category_counts.py
test/test_entries_api.py
test/test_entry.py
test/test_entry_currency.py
test/test_entry_import.py
test/test_me.py
test/test_me_currency.py
test/test_me_limits.py
test/test_me_migration.py
test/test_me_pro.py
test/test_me_pro_payment.py
test/test_me_pro_trial.py
test/test_misc_api.py
toshl_api.egg-info/PKG-INFO
toshl_api.egg-info/SOURCES.txt
toshl_api.egg-info/dependency_links.txt
toshl_api.egg-info/requires.txt
toshl_api.egg-info/top_level.txt
toshl_swagger_client/__init__.py
toshl_swagger_client/api_client.py
toshl_swagger_client/configuration.py
toshl_swagger_client/rest.py
toshl_swagger_client/api/__init__.py
toshl_swagger_client/api/accounts_api.py
toshl_swagger_client/api/bank_api.py
toshl_swagger_client/api/categories_api.py
toshl_swagger_client/api/entries_api.py
toshl_swagger_client/api/misc_api.py
toshl_swagger_client/models/__init__.py
toshl_swagger_client/models/account.py
toshl_swagger_client/models/account_currency.py
toshl_swagger_client/models/account_daily_sum_median.py
toshl_swagger_client/models/bankconnection.py
toshl_swagger_client/models/category.py
toshl_swagger_client/models/category_counts.py
toshl_swagger_client/models/entry.py
toshl_swagger_client/models/entry_currency.py
toshl_swagger_client/models/entry_import.py
toshl_swagger_client/models/me.py
toshl_swagger_client/models/me_currency.py
toshl_swagger_client/models/me_limits.py
toshl_swagger_client/models/me_migration.py
toshl_swagger_client/models/me_pro.py
toshl_swagger_client/models/me_pro_payment.py
toshl_swagger_client/models/me_pro_trial.py