Metadata-Version: 1.0
Name: toshl-api
Version: 1.0.4
Summary: Toshl
Home-page: UNKNOWN
Author: UNKNOWN
Author-email: UNKNOWN
License: UNKNOWN
Keywords: Swagger,Toshl
Platform: UNKNOWN
